emipy/__init__.py
emipy/exporttocalliope.py
emipy/processdata.py
emipy/rawdata.py
emipy/visualizedata.py
emipy/configuration/configuration.ini
emipy-0.1.1.dist-info/LICENSE
emipy-0.1.1.dist-info/METADATA
emipy-0.1.1.dist-info/WHEEL
emipy-0.1.1.dist-info/top_level.txt
emipy-0.1.1.dist-info/RECORD
