Metadata-Version: 2.1
Name: emipy
Version: 0.1.1
Summary: Python package for emission data analysis based on the E-PRTR database.
Home-page: https://jugit.fz-juelich.de/network-science-group/emipy
Author: Florian Overberg, Philipp C. Böttcher, Simon Morgenthaler
Author-email: p.boettcher@fz-juelich.de
License: UNKNOWN
Project-URL: Documentation, https://emipy.readthedocs.io/en/latest/
Project-URL: Source, https://jugit.fz-juelich.de/network-science-group/emipy
Platform: UNKNOWN
Classifier: Programming Language :: Python :: 3
Classifier: License :: OSI Approved :: MIT License
Classifier: Operating System :: OS Independent
Requires-Python: >=3.6
Requires-Dist: matplotlib (>=3.3.1)
Requires-Dist: requests (>=2.24.0)
Requires-Dist: configparser (>=5.0.0)
Requires-Dist: pandas (>=1.1.1)
Requires-Dist: ruamel.yaml (>=0.16.12)
Requires-Dist: descartes (>=1.1.0)
Requires-Dist: openpyxl (>=3.0.6)
Requires-Dist: xlrd (>=1.0.0)
